api/__init__.py
wx2b-0.0.1.dist-info/LICENSE
wx2b-0.0.1.dist-info/METADATA
wx2b-0.0.1.dist-info/WHEEL
wx2b-0.0.1.dist-info/top_level.txt
wx2b-0.0.1.dist-info/RECORD
