Metadata-Version: 2.1
Name: wx2b
Version: 0.0.1
Summary: wx2b
Home-page: https://github.com/pypa/sampleproject
Author: lookie
Author-email: ilookie@163.com
License: UNKNOWN
Platform: UNKNOWN
Classifier: Programming Language :: Python :: 3
Classifier: License :: OSI Approved :: MIT License
Classifier: Operating System :: OS Independent
Requires-Python: >=3.6
